skylers_cli/__init__.py
skylers_cli/cli/__init__.py
skylers_cli/cli/main.py
skylers_cli/core/__init__.py
skylers_cli/core/bootstrap/__init__.py
skylers_cli/core/bootstrap/system.py
skylers_cli/core/bootstrap/system_template/.bashrc
skylers_cli/core/bootstrap/system_template/__init__.py
skylers_cli/core/bootstrap/system_template/compton.conf
skylers_cli/core/bootstrap/system_template/i3_config
skylers_cli/core/bootstrap/system_template/inputrc
skylers_cli/core/bootstrap/system_template/tmux.conf
skylers_cli-1.0.2.dist-info/METADATA
skylers_cli-1.0.2.dist-info/WHEEL
skylers_cli-1.0.2.dist-info/entry_points.txt
skylers_cli-1.0.2.dist-info/RECORD
