Metadata-Version: 2.1
Name: skylers-cli
Version: 1.0.2
Summary: Skyler's toolbox of handy CLI utils
Author: bouldersky
Author-email: skyarnold1@me.com
Requires-Python: >=3.9,<4.0
Classifier: Programming Language :: Python :: 3
Classifier: Programming Language :: Python :: 3.9
Classifier: Programming Language :: Python :: 3.10
Classifier: Programming Language :: Python :: 3.11
Classifier: Programming Language :: Python :: 3.12
Requires-Dist: chevron (>=0.14.0,<0.15.0)
Requires-Dist: pydicom (>=2.4.4,<3.0.0)
Requires-Dist: pylibmagic (>=0.5.0,<0.6.0)
Requires-Dist: python-magic (>=0.4.27,<0.5.0)
Requires-Dist: typer[all] (>=0.6.1,<0.7.0)
